actinia_stac_plugin/__init__.py
actinia_stac_plugin/endpoints.py
actinia_stac_plugin/main.py
actinia_stac_plugin/wsgi.py
actinia_stac_plugin/api/__init__.py
actinia_stac_plugin/api/stac.py
actinia_stac_plugin/api/stac_catalogs.py
actinia_stac_plugin/api/stac_collection_id.py
actinia_stac_plugin/api/stac_collections.py
actinia_stac_plugin/api/stac_instance_id.py
actinia_stac_plugin/api/stac_instances.py
actinia_stac_plugin/api/stac_items.py
actinia_stac_plugin/apidocs/stac.py
actinia_stac_plugin/apidocs/stac_catalogs_docs.py
actinia_stac_plugin/apidocs/stac_collections_docs.py
actinia_stac_plugin/apidocs/stac_collections_id_docs.py
actinia_stac_plugin/apidocs/stac_instances_docs.py
actinia_stac_plugin/apidocs/stac_instances_id_docs.py
actinia_stac_plugin/apidocs/stac_items_docs.py
actinia_stac_plugin/core/__init__.py
actinia_stac_plugin/core/common.py
actinia_stac_plugin/core/stac.py
actinia_stac_plugin/core/stac_catalogs.py
actinia_stac_plugin/core/stac_collection_id.py
actinia_stac_plugin/core/stac_collections.py
actinia_stac_plugin/core/stac_instance_id.py
actinia_stac_plugin/core/stac_instances.py
actinia_stac_plugin/core/stac_items.py
actinia_stac_plugin/core/stac_kvdb_interface.py
actinia_stac_plugin/resources/__init__.py
actinia_stac_plugin/resources/config.py
actinia_stac_plugin/resources/log.py
actinia_stac_plugin-0.4.0.dist-info/licenses/LICENSE.txt
actinia_stac_plugin-0.4.0.dist-info/METADATA
actinia_stac_plugin-0.4.0.dist-info/WHEEL
actinia_stac_plugin-0.4.0.dist-info/top_level.txt
actinia_stac_plugin-0.4.0.dist-info/RECORD
