Metadata-Version: 2.4
Name: actinia-stac-plugin
Version: 0.4.0
Summary: A (RESTFUL) Flask application which implements STAC collections into actinia
Author: Jorge Herrera, Carmen Tawalika, Marc Jansen, Lina Krisztian, Markus Neteler, Markus Metz, Anika Weinmann
Project-URL: Homepage, https://github.com/mundialis/actinia-stac-plugin
Project-URL: Tutorial, https://mundialis.github.io/actinia_core
Project-URL: API_Docs, https://redocly.github.io/redoc/?url=https://actinia.mundialis.de/latest/swagger.json
Keywords: processing,earth observation,cloud-based processing,rest api,gis,grass gis,osgeo,stac
Classifier: License :: OSI Approved :: GNU General Public License v3 or later (GPLv3+)
Classifier: Programming Language :: Python :: 3
Requires-Python: >=3.8
License-File: LICENSE.txt
Requires-Dist: actinia-api>=3.7.0
Requires-Dist: colorlog>=4.2.1
Requires-Dist: Flask
Requires-Dist: Flask-Cors
Requires-Dist: Flask-RESTful
Requires-Dist: flask-restful-swagger-2
Requires-Dist: python-json-logger
Requires-Dist: rasterio
Requires-Dist: stac-validator>=2.2.0
Provides-Extra: test
Requires-Dist: pytest; extra == "test"
Requires-Dist: pytest-cov; extra == "test"
Requires-Dist: pwgen; extra == "test"
Dynamic: license-file
